{
  "mode": "live",
  "task_id": "09231701-4117-0121-0000-aa24032db60b",
  "query": "site:truyena.net casino",
  "depth": 100,
  "extracted": [
    {
      "title": "Nh\u1eefng Tr\u00f2 Ch\u01a1i Tr\u1ef1c Tuy\u1ebfn Hot Nh\u1ea5t Trong Ng\u00e0nh C\u00f4ng ...",
      "url": "https://truyena.net/the-hottest-online-games-in-the-gaming-industry.html",
      "snippet": "T\u1ea5t nhi\u00ean, kh\u00f4ng ch\u1ec9 baccarat, m\u00e0 t\u1ea5t c\u1ea3 c\u00e1c tr\u00f2 ch\u01a1i kh\u00e1c, bao g\u1ed3m c\u1ea3 blackjack v\u00e0 roulette, \u0111\u1ec1u c\u00f3 s\u1eb5n b\u1eb1ng ti\u1ebfng Nh\u1eadt. V\u00ec \u0111\u00e2y l\u00e0 tr\u00f2 ch\u01a1i tr\u1ef1c tuy\u1ebfn thay\u00a0...",
      "rank_absolute": 1,
      "rank_group": 1,
      "result_type": "items"
    }
  ]
}